MANIFEST.in
README.rst
setup.py
photos/__init__.py
photos/bootstrap.py
photos/helpers.py
photos/partials.py
photos/controllers/__init__.py
photos/controllers/root.py
photos/lib/__init__.py
photos/model/__init__.py
photos/model/models.py
photos/public/__init__.py
photos/public/css/jquery.lightbox-0.5.css
photos/public/css/style.css
photos/public/images/gallery_default.png
photos/public/images/lightbox-blank.gif
photos/public/images/lightbox-btn-close.gif
photos/public/images/lightbox-btn-next.gif
photos/public/images/lightbox-btn-prev.gif
photos/public/images/lightbox-ico-loading.gif
photos/public/js/jquery.js
photos/public/js/jquery.lightbox-0.5.min.js
photos/templates/__init__.py
photos/templates/albums_partial.html
photos/templates/albums_partial.xhtml
photos/templates/gallery.html
photos/templates/gallery.xhtml
photos/templates/gallery_partial.html
photos/templates/gallery_partial.xhtml
photos/templates/index.html
photos/templates/index.xhtml
photos/templates/photo.html
photos/templates/photo.xhtml
photos/templates/manage/__init__.py
tgapp_photos.egg-info/PKG-INFO
tgapp_photos.egg-info/SOURCES.txt
tgapp_photos.egg-info/dependency_links.txt
tgapp_photos.egg-info/entry_points.txt
tgapp_photos.egg-info/not-zip-safe
tgapp_photos.egg-info/paster_plugins.txt
tgapp_photos.egg-info/requires.txt
tgapp_photos.egg-info/top_level.txt