Metadata-Version: 1.0
Name: tgapp-photos
Version: 0.3.0
Summary: Minimal Pluggable Photogallery for TurboGears2, EasyCrudRestController based for management
Home-page: http://bitbucket.org/_amol_/tgapp-photos
Author: Alessandro Molina
Author-email: alessandro.molina@axant.it
License: UNKNOWN
Keywords: turbogears2.application
Platform: UNKNOWN
